failsafe_kill/LICENSE
failsafe_kill/README.MD
failsafe_kill/__init__.py
failsafe_kill/requirements.txt
failsafe_kill/thirdparty.json
failsafe_kill-0.10.dist-info/LICENSE.rst
failsafe_kill-0.10.dist-info/METADATA
failsafe_kill-0.10.dist-info/WHEEL
failsafe_kill-0.10.dist-info/top_level.txt
failsafe_kill-0.10.dist-info/RECORD
